mega/__init__.py
mega/__version__.py
mega/mega.py
mega-0.2.11.dist-info/LICENSE
mega-0.2.11.dist-info/METADATA
mega-0.2.11.dist-info/WHEEL
mega-0.2.11.dist-info/entry_points.txt
mega-0.2.11.dist-info/top_level.txt
mega-0.2.11.dist-info/RECORD
