Metadata-Version: 2.1
Name: mega
Version: 0.2.11
Summary: Python web scraper for DMCA evangelists.
Home-page: https://github.com/bl0nd/mega
Author: Jason Phan
Author-email: xor.jasonphan@gmail.com
License: MIT
Platform: UNKNOWN
Classifier: Development Status :: 5 - Production/Stable
Classifier: Intended Audience :: End Users/Desktop
Classifier: Natural Language :: English
Classifier: License :: OSI Approved :: MIT License
Classifier: Programming Language :: Python
Classifier: Programming Language :: Python :: 3.7
Requires-Python: >=3.7
